iac_scan_runner/__init__.py
iac_scan_runner/api.py
iac_scan_runner/cli.py
iac_scan_runner/object_store.py
iac_scan_runner/utils.py
iac_scan_runner/vars.py
iac_scan_runner/asset/response.html
iac_scan_runner/asset/table_basic.html
iac_scan_runner/asset/table_info.html
iac_scan_runner/asset/table_passed.html
iac_scan_runner/asset/table_problem.html
iac_scan_runner/checks/__init__.py
iac_scan_runner/checks/ansible_lint.py
iac_scan_runner/checks/bandit.py
iac_scan_runner/checks/checkstyle.py
iac_scan_runner/checks/cloc.py
iac_scan_runner/checks/es_lint.py
iac_scan_runner/checks/git_leaks.py
iac_scan_runner/checks/git_secrets.py
iac_scan_runner/checks/gixy.py
iac_scan_runner/checks/hadolint.py
iac_scan_runner/checks/htmlhint.py
iac_scan_runner/checks/markdown_lint.py
iac_scan_runner/checks/opera_tosca_parser.py
iac_scan_runner/checks/pylint.py
iac_scan_runner/checks/pyup_safety.py
iac_scan_runner/checks/shellcheck.py
iac_scan_runner/checks/snyk.py
iac_scan_runner/checks/sonar_scanner.py
iac_scan_runner/checks/steampunk_spotter.py
iac_scan_runner/checks/stylelint.py
iac_scan_runner/checks/terrascan.py
iac_scan_runner/checks/tflint.py
iac_scan_runner/checks/tfsec.py
iac_scan_runner/checks/ts_lint.py
iac_scan_runner/checks/yamllint.py
iac_scan_runner/enums/__init__.py
iac_scan_runner/enums/check_target_entity_type.py
iac_scan_runner/enums/scan_response_type.py
iac_scan_runner/functionality/__init__.py
iac_scan_runner/functionality/check_output.py
iac_scan_runner/functionality/cleanup_old_scans.py
iac_scan_runner/functionality/compatibility.py
iac_scan_runner/functionality/project_config.py
iac_scan_runner/functionality/results_persistence.py
iac_scan_runner/functionality/results_summary.py
iac_scan_runner/functionality/scan_project.py
iac_scan_runner/functionality/scan_runner.py
iac_scan_runner/interface/__init__.py
iac_scan_runner/interface/check.py
iac_scan_runner/model/ConfigureCheck.py
iac_scan_runner/model/Scan.py
iac_scan_runner/routers/__init__.py
iac_scan_runner-0.4.3.dist-info/LICENSE
iac_scan_runner-0.4.3.dist-info/METADATA
iac_scan_runner-0.4.3.dist-info/WHEEL
iac_scan_runner-0.4.3.dist-info/entry_points.txt
iac_scan_runner-0.4.3.dist-info/top_level.txt
iac_scan_runner-0.4.3.dist-info/zip-safe
iac_scan_runner-0.4.3.dist-info/RECORD
