Metadata-Version: 2.1
Name: iac-scan-runner
Version: 0.4.3
Summary: IaC Scan Runner CLI
Home-page: https://github.com/xlab-si/iac-scan-runner
Author: XLAB d.o.o.
Author-email: pypi@xlab.si
Maintainer: xOpera team
Maintainer-email: xopera@xlab.si
Project-URL: Source Code, https://github.com/xlab-si/iac-scan-runner
Project-URL: Bug Tracker, https://github.com/xlab-si/iac-scan-runner/issues
Project-URL: Documentation, https://xlab-si.github.io/iac-scanner-docs/
Project-URL: Discussions, https://github.com/xlab-si/iac-scan-runner/discussions
Project-URL: Releases, https://github.com/xlab-si/iac-scan-runner/releases
Project-URL: Pre-releases, https://test.pypi.org/project/iac-scan-runner/#history
Project-URL: Docker, https://hub.docker.com/r/xscanner/runner
Project-URL: CI, https://github.com/xlab-si/iac-scan-runner/actions
Keywords: IaC,scan,scanner,inspector,runner,api,cli,quality
Classifier: Development Status :: 2 - Pre-Alpha
Classifier: Environment :: Console
Classifier: Intended Audience :: Developers
Classifier: Intended Audience :: System Administrators
Classifier: Intended Audience :: Science/Research
Classifier: Intended Audience :: Information Technology
Classifier: License :: OSI Approved :: Apache Software License
Classifier: Operating System :: POSIX
Classifier: Programming Language :: Python
Classifier: Programming Language :: Python :: 3
Classifier: Programming Language :: Python :: 3.8
Classifier: Programming Language :: Python :: 3.9
Classifier: Programming Language :: Python :: 3.10
Classifier: Programming Language :: Python :: 3.11
Classifier: Topic :: Software Development
Classifier: Topic :: Software Development :: Bug Tracking
Classifier: Topic :: Software Development :: Quality Assurance
Classifier: Topic :: Software Development :: Testing
Classifier: Topic :: Software Development :: Libraries
Classifier: Topic :: Software Development :: Libraries :: Python Modules
License-File: LICENSE
Requires-Dist: typer
Requires-Dist: fastapi
Requires-Dist: uvicorn[standard]
Requires-Dist: python-multipart
Requires-Dist: pydantic
Requires-Dist: content-size-limit-asgi
Requires-Dist: PyYAML
Requires-Dist: pymongo ==4.2.0
Requires-Dist: schedule ==1.1.0
